nyro/__init__.py
nyro/cli/__init__.py
nyro/cli/interactive.py
nyro/cli/main.py
nyro/core/__init__.py
nyro/core/client.py
nyro/core/operations.py
nyro/core/profiles.py
nyro/musical/__init__.py
nyro/musical/composer.py
nyro/musical/ledger.py
nyro-0.1.3.dist-info/licenses/LICENSE
testing/ASSEMBLY_LEDGER.md
testing/test_framework.py
nyro-0.1.3.dist-info/METADATA
nyro-0.1.3.dist-info/WHEEL
nyro-0.1.3.dist-info/entry_points.txt
nyro-0.1.3.dist-info/top_level.txt
nyro-0.1.3.dist-info/RECORD
