Metadata-Version: 2.4
Name: nyro
Version: 0.1.3
Summary: ♠️🌿🎸🧵 Unified Redis Operations Package - Consolidating 13+ bash scripts
Home-page: https://github.com/gerico1007/nyro
Author: Jerry ⚡ G.Music Assembly Team
Author-email: "Jerry ⚡ G.Music Assembly Team" <gerico@jgwill.com>
License: MIT
Project-URL: Homepage, https://github.com/gerico1007/nyro
Project-URL: Documentation, https://github.com/gerico1007/nyro/wiki
Project-URL: Repository, https://github.com/gerico1007/nyro.git
Project-URL: Bug Reports, https://github.com/gerico1007/nyro/issues
Project-URL: G.Music Assembly, https://github.com/gerico1007/nyro/tree/main/assembly
Keywords: redis,upstash,database,cli,music,assembly,consolidation
Classifier: Development Status :: 4 - Beta
Classifier: Intended Audience :: Developers
Classifier: License :: OSI Approved :: MIT License
Classifier: Operating System :: OS Independent
Classifier: Programming Language :: Python :: 3
Classifier: Programming Language :: Python :: 3.7
Classifier: Programming Language :: Python :: 3.8
Classifier: Programming Language :: Python :: 3.9
Classifier: Programming Language :: Python :: 3.10
Classifier: Programming Language :: Python :: 3.11
Classifier: Programming Language :: Python :: 3.12
Classifier: Topic :: Database :: Front-Ends
Classifier: Topic :: Software Development :: Libraries :: Python Modules
Classifier: Topic :: System :: Systems Administration
Classifier: Topic :: Multimedia :: Sound/Audio :: MIDI
Requires-Python: >=3.7
License-File: LICENSE
Requires-Dist: requests>=2.25.0
Provides-Extra: musical
Requires-Dist: musicpy>=6.0.0; extra == "musical"
Requires-Dist: mido>=1.2.0; extra == "musical"
Provides-Extra: dev
Requires-Dist: pytest>=6.0.0; extra == "dev"
Requires-Dist: pytest-cov>=2.10.0; extra == "dev"
Requires-Dist: black>=21.0.0; extra == "dev"
Requires-Dist: flake8>=3.8.0; extra == "dev"
Requires-Dist: mypy>=0.800; extra == "dev"
Requires-Dist: build>=0.8.0; extra == "dev"
Requires-Dist: twine>=4.0.0; extra == "dev"
Provides-Extra: all
Requires-Dist: musicpy>=6.0.0; extra == "all"
Requires-Dist: mido>=1.2.0; extra == "all"
Requires-Dist: pytest>=6.0.0; extra == "all"
Requires-Dist: pytest-cov>=2.10.0; extra == "all"
Requires-Dist: black>=21.0.0; extra == "all"
Requires-Dist: flake8>=3.8.0; extra == "all"
Requires-Dist: mypy>=0.800; extra == "all"
Requires-Dist: build>=0.8.0; extra == "all"
Requires-Dist: twine>=4.0.0; extra == "all"
Dynamic: author
Dynamic: home-page
Dynamic: license-file
Dynamic: requires-python
